{ "title" : "Criminal Law (Defence and the Dwelling) Bill 2010 - Report Stage Amendment 2. That the words proposed to be deleted stand.","date" : { "date" : "2011-11-24","time" : "13:42:00","weekday" : "Thursday"},"yes" : ["Breen, Pat","Butler, Ray","Buttimer, Jerry","Byrne, Catherine","Carey, Joe","Coffey, Paudie","Collins, Áine","Conlan, Seán","Connaughton, Paul J.","Coonan, Noel","Corcoran Kennedy, Marcella","Creed, Michael","Deasy, John","Deering, Pat","Doherty, Regina","Donohoe, Paschal","Durkan, Bernard J.","English, Damien","Farrell, Alan","Feighan, Frank","Fitzpatrick, Peter","Griffin, Brendan","Harrington, Noel","Harris, Simon","Hayes, Tom","Heydon, Martin","Keating, Derek","Kehoe, Paul","Kyne, Seán","Lawlor, Anthony","Mathews, Peter","McFadden, Nicky","McGinley, Dinny","McHugh, Joe","McLoughlin, Tony","Mitchell, Olivia","Mulherin, Michelle","Murphy, Eoghan","Neville, Dan","O'Donnell, Kieran","O'Donovan, Patrick","Shatter, Alan","Stanton, David","Timmins, Billy","Twomey, Liam","Walsh, Brian","Broughan, Thomas P.","Conaghan, Michael","Conway, Ciara","Dowds, Robert","Ferris, Anne","Hannigan, Dominic","Keaveney, Colm","Kenny, Seán","Lynch, Ciarán","Lynch, Kathleen","Lyons, John","Maloney, Eamonn","McCarthy, Michael","McNamara, Michael","Nash, Gerald","Nolan, Derek","Nulty, Patrick","Ó Ríordáin, Aodhán","Phelan, Ann","Ryan, Brendan","Sherlock, Sean","Shortall, Róisín","Spring, Arthur","Tuffy, Joanna","White, Alex"],"no" : ["Cowen, Barry","Dooley, Timmy","Kirk, Seamus","Martin, Micheál","McConalogue, Charlie","McGuinness, John","Ó Cuív, Éamon","Ó Fearghaíl, Seán","Smith, Brendan","Troy, Robert","Daly, Clare","Flanagan, Luke 'Ming'","Fleming, Tom","Healy, Seamus","McGrath, Finian","McGrath, Mattie","Murphy, Catherine","Pringle, Thomas","Ross, Shane","Wallace, Mick","Collins, Joan","Colreavy, Michael","Doherty, Pearse","Ferris, Martin","Mac Lochlainn, Pádraig","McDonald, Mary Lou","McLellan, Sandra","O'Brien, Jonathan","Ó Caoláin, Caoimhghín","Ó Snodaigh, Aengus","Stanley, Brian","Higgins, Joe"], "absent" : ["Browne, John","Calleary, Dara","Collins, Niall","Fleming, Sean","Kelleher, Billy","Kitt, Michael P.","McGrath, Michael","Moynihan, Michael","O'Dea, Willie","Bannon, James","Barry, Tom","Bruton, Richard","Cannon, Ciarán","Coveney, Simon","Creighton, Lucinda","Daly, Jim","Deenihan, Jimmy","Doyle, Andrew","Fitzgerald, Frances","Flanagan, Charles","Flanagan, Terence","Hayes, Brian","Hogan, Phil","Humphreys, Heather","Kenny, Enda","McEntee, Shane","Mitchell O'Connor, Mary","Murphy, Dara","Naughten, Denis","Noonan, Michael","O'Dowd, Fergus","O'Mahony, John","O'Reilly, Joe","Perry, John","Phelan, John Paul","Reilly, James","Ring, Michael","Varadkar, Leo","Donnelly, Stephen S.","Grealish, Noel","Halligan, John","Healy-Rae, Michael","Lowry, Michael","O'Sullivan, Maureen","Burton, Joan","Byrne, Eric","Costello, Joe","Gilmore, Eamon","Howlin, Brendan","Humphreys, Kevin","Kelly, Alan","O'Sullivan, Jan","Penrose, Willie","Quinn, Ruairí","Rabbitte, Pat","Stagg, Emmet","Wall, Jack","Boyd Barrett, Richard","Adams, Gerry","Crowe, Seán","Ellis, Dessie","Tóibín, Peadar","Barrett, Seán"] }