{ "title" : "Motion re Proposed approval by Dáil Éireann of the terms of the Free Trade agreement between the EU and the Republic of Korea. That the motion be agreed to.","date" : { "date" : "2011-07-21","time" : "11:52:00","weekday" : "Thursday"},"yes" : ["Calleary, Dara","Cowen, Barry","Dooley, Timmy","Fleming, Sean","Kelleher, Billy","Kitt, Michael P.","McGrath, Michael","Ó Fearghaíl, Seán","Smith, Brendan","Bannon, James","Barry, Tom","Breen, Pat","Butler, Ray","Buttimer, Jerry","Byrne, Catherine","Carey, Joe","Coffey, Paudie","Collins, Áine","Conlan, Seán","Connaughton, Paul J.","Coonan, Noel","Corcoran Kennedy, Marcella","Creed, Michael","Daly, Jim","Deasy, John","Deenihan, Jimmy","Deering, Pat","Doherty, Regina","Doyle, Andrew","Durkan, Bernard J.","English, Damien","Farrell, Alan","Feighan, Frank","Fitzgerald, Frances","Fitzpatrick, Peter","Flanagan, Charles","Flanagan, Terence","Griffin, Brendan","Harrington, Noel","Harris, Simon","Hayes, Brian","Hayes, Tom","Heydon, Martin","Humphreys, Heather","Keating, Derek","Kehoe, Paul","Kyne, Seán","Lawlor, Anthony","Mathews, Peter","McEntee, Shane","McFadden, Nicky","McGinley, Dinny","McLoughlin, Tony","Mulherin, Michelle","Murphy, Dara","Murphy, Eoghan","Naughten, Denis","Neville, Dan","O'Donnell, Kieran","O'Donovan, Patrick","O'Dowd, Fergus","O'Mahony, John","O'Reilly, Joe","Phelan, John Paul","Reilly, James","Shatter, Alan","Stanton, David","Timmins, Billy","Twomey, Liam","Donnelly, Stephen S.","Broughan, Thomas P.","Byrne, Eric","Conaghan, Michael","Costello, Joe","Dowds, Robert","Ferris, Anne","Gilmore, Eamon","Humphreys, Kevin","Keaveney, Colm","Kenny, Seán","Lynch, Ciarán","Lynch, Kathleen","Lyons, John","Maloney, Eamonn","McCarthy, Michael","O'Sullivan, Jan","Ó Ríordáin, Aodhán","Phelan, Ann","Ryan, Brendan","Shortall, Róisín","Spring, Arthur","Wall, Jack","White, Alex"],"no" : ["Daly, Clare","Flanagan, Luke 'Ming'","Fleming, Tom","Healy, Seamus","McGrath, Finian","Murphy, Catherine","O'Sullivan, Maureen","Pringle, Thomas","Wallace, Mick","Boyd Barrett, Richard","Collins, Joan","Colreavy, Michael","Crowe, Seán","Doherty, Pearse","McLellan, Sandra","O'Brien, Jonathan","Ó Caoláin, Caoimhghín","Ó Snodaigh, Aengus","Stanley, Brian","Tóibín, Peadar","Higgins, Joe"], "absent" : ["Browne, John","Collins, Niall","Kirk, Seamus","Martin, Micheál","McConalogue, Charlie","McGuinness, John","Moynihan, Michael","O'Dea, Willie","Ó Cuív, Éamon","Troy, Robert","Bruton, Richard","Cannon, Ciarán","Coveney, Simon","Creighton, Lucinda","Donohoe, Paschal","Hogan, Phil","Kenny, Enda","McHugh, Joe","Mitchell O'Connor, Mary","Mitchell, Olivia","Noonan, Michael","Perry, John","Ring, Michael","Varadkar, Leo","Walsh, Brian","Grealish, Noel","Halligan, John","Healy-Rae, Michael","Lowry, Michael","McGrath, Mattie","Ross, Shane","Burton, Joan","Conway, Ciara","Hannigan, Dominic","Howlin, Brendan","Kelly, Alan","McNamara, Michael","Nash, Gerald","Nolan, Derek","Nulty, Patrick","Penrose, Willie","Quinn, Ruairí","Rabbitte, Pat","Sherlock, Sean","Stagg, Emmet","Tuffy, Joanna","Adams, Gerry","Ellis, Dessie","Ferris, Martin","Mac Lochlainn, Pádraig","McDonald, Mary Lou","Barrett, Seán"] }