{ "title" : "Euro Loan Facility (Amendment) Bill 2012. That in respect of each of the sections undisposed of, the section is hereby agreed to in Committee; Schedule and Title is agreed to in Committee; Bill is accordingly reported to the House without amdt; Fourth Stage is hereby completed; and the Bill is hereby passed.","date" : { "date" : "2012-03-07","time" : "19:30:00","weekday" : "Wednesday"},"yes" : ["Browne, John","Calleary, Dara","Cowen, Barry","Dooley, Timmy","Fleming, Sean","Kirk, Seamus","Kitt, Michael P.","Martin, Micheál","McConalogue, Charlie","McGrath, Michael","Ó Cuív, Éamon","Ó Fearghaíl, Seán","Smith, Brendan","Troy, Robert","Bannon, James","Barry, Tom","Breen, Pat","Bruton, Richard","Buttimer, Jerry","Byrne, Catherine","Carey, Joe","Coffey, Paudie","Collins, Áine","Conlan, Seán","Connaughton, Paul J.","Coonan, Noel","Corcoran Kennedy, Marcella","Coveney, Simon","Creed, Michael","Creighton, Lucinda","Daly, Jim","Deasy, John","Deenihan, Jimmy","Doherty, Regina","Donohoe, Paschal","Doyle, Andrew","Durkan, Bernard J.","English, Damien","Farrell, Alan","Feighan, Frank","Fitzgerald, Frances","Fitzpatrick, Peter","Flanagan, Charles","Flanagan, Terence","Griffin, Brendan","Harrington, Noel","Harris, Simon","Hayes, Tom","Heydon, Martin","Humphreys, Heather","Kehoe, Paul","Kenny, Enda","Kyne, Seán","Lawlor, Anthony","Mathews, Peter","McEntee, Shane","McFadden, Nicky","McGinley, Dinny","McLoughlin, Tony","Mitchell O'Connor, Mary","Mitchell, Olivia","Mulherin, Michelle","Murphy, Dara","Murphy, Eoghan","Naughten, Denis","Neville, Dan","O'Donnell, Kieran","O'Donovan, Patrick","O'Mahony, John","O'Reilly, Joe","Phelan, John Paul","Reilly, James","Ring, Michael","Stanton, David","Timmins, Billy","Twomey, Liam","Varadkar, Leo","Walsh, Brian","Donnelly, Stephen S.","Healy-Rae, Michael","McGrath, Mattie","Ross, Shane","Burton, Joan","Byrne, Eric","Dowds, Robert","Hannigan, Dominic","Humphreys, Kevin","Keaveney, Colm","Kenny, Seán","Lynch, Ciarán","Lynch, Kathleen","Lyons, John","Maloney, Eamonn","McCarthy, Michael","McNamara, Michael","Nash, Gerald","Nolan, Derek","Nulty, Patrick","Ó Ríordáin, Aodhán","Phelan, Ann","Rabbitte, Pat","Ryan, Brendan","Sherlock, Sean","Spring, Arthur","Stagg, Emmet","Tuffy, Joanna","Wall, Jack","White, Alex"],"no" : ["Daly, Clare","Flanagan, Luke 'Ming'","Fleming, Tom","Halligan, John","Healy, Seamus","McGrath, Finian","Murphy, Catherine","Pringle, Thomas","Wallace, Mick","Boyd Barrett, Richard","Collins, Joan","Colreavy, Michael","Doherty, Pearse","Ferris, Martin","Mac Lochlainn, Pádraig","McLellan, Sandra","Ó Caoláin, Caoimhghín","Ó Snodaigh, Aengus","Stanley, Brian","Tóibín, Peadar"], "absent" : ["Collins, Niall","Kelleher, Billy","McGuinness, John","Moynihan, Michael","O'Dea, Willie","Butler, Ray","Cannon, Ciarán","Deering, Pat","Hayes, Brian","Hogan, Phil","Keating, Derek","McHugh, Joe","Noonan, Michael","O'Dowd, Fergus","Perry, John","Shatter, Alan","Grealish, Noel","Lowry, Michael","O'Sullivan, Maureen","Broughan, Thomas P.","Conaghan, Michael","Conway, Ciara","Costello, Joe","Ferris, Anne","Gilmore, Eamon","Howlin, Brendan","Kelly, Alan","O'Sullivan, Jan","Penrose, Willie","Quinn, Ruairí","Shortall, Róisín","Adams, Gerry","Crowe, Seán","Ellis, Dessie","McDonald, Mary Lou","O'Brien, Jonathan","Higgins, Joe","Barrett, Seán"] }