{ "title" : "Health (Alteration of Criteria for Eligibility) Bill 2013 - Committee and Remaining Stages: That each section undisposed of is agreed to in Ctte; the Title is agreed to; the Bill is reported to the House without amendment; Fourth Stage is completed and the Bill is passed","date" : { "date" : "2013-03-26","time" : "20:08:00","weekday" : "Tuesday"},"yes" : ["Bannon, James","Butler, Ray","Buttimer, Jerry","Byrne, Catherine","Carey, Joe","Collins, Áine","Conlan, Seán","Coonan, Noel","Coveney, Simon","Creed, Michael","Daly, Jim","Deasy, John","Deering, Pat","Donohoe, Paschal","Doyle, Andrew","Durkan, Bernard J.","Farrell, Alan","Fitzpatrick, Peter","Flanagan, Charles","Harris, Simon","Heydon, Martin","Humphreys, Heather","Kehoe, Paul","Kyne, Seán","Lawlor, Anthony","McGinley, Dinny","Mitchell, Olivia","Mulherin, Michelle","Murphy, Dara","Neville, Dan","Noonan, Michael","O'Donnell, Kieran","O'Donovan, Patrick","O'Dowd, Fergus","O'Mahony, John","O'Reilly, Joe","Phelan, John Paul","Reilly, James","Shatter, Alan","Timmins, Billy","Byrne, Eric","Conaghan, Michael","Conway, Ciara","Costello, Joe","Dowds, Robert","Ferris, Anne","Howlin, Brendan","Humphreys, Kevin","Kenny, Seán","Lynch, Ciarán","Maloney, Eamonn","Nolan, Derek","O'Sullivan, Jan","Ó Ríordáin, Aodhán","Rabbitte, Pat","Ryan, Brendan","Stagg, Emmet","Wall, Jack","White, Alex"],"no" : ["Calleary, Dara","Kelleher, Billy","McConalogue, Charlie","McGrath, Michael","Moynihan, Michael","Ó Cuív, Éamon","Ó Fearghaíl, Seán","Healy, Seamus","Murphy, Catherine","O'Sullivan, Maureen","Collins, Joan","Colreavy, Michael","Crowe, Seán","Doherty, Pearse","Ferris, Martin","Mac Lochlainn, Pádraig","O'Brien, Jonathan","Ó Caoláin, Caoimhghín","Ó Snodaigh, Aengus","Stanley, Brian","Higgins, Joe"], "absent" : ["Browne, John","Collins, Niall","Cowen, Barry","Dooley, Timmy","Fleming, Sean","Kirk, Seamus","Kitt, Michael P.","Martin, Micheál","McGuinness, John","O'Dea, Willie","Smith, Brendan","Troy, Robert","Barry, Tom","Breen, Pat","Bruton, Richard","Cannon, Ciarán","Coffey, Paudie","Connaughton, Paul J.","Corcoran Kennedy, Marcella","Creighton, Lucinda","Deenihan, Jimmy","Doherty, Regina","English, Damien","Feighan, Frank","Fitzgerald, Frances","Flanagan, Terence","Griffin, Brendan","Harrington, Noel","Hayes, Brian","Hayes, Tom","Hogan, Phil","Keating, Derek","Kenny, Enda","Mathews, Peter","McEntee, Shane","McFadden, Nicky","McHugh, Joe","McLoughlin, Tony","Mitchell O'Connor, Mary","Murphy, Eoghan","Naughten, Denis","Perry, John","Ring, Michael","Stanton, David","Twomey, Liam","Varadkar, Leo","Walsh, Brian","Daly, Clare","Donnelly, Stephen S.","Flanagan, Luke 'Ming'","Fleming, Tom","Grealish, Noel","Halligan, John","Healy-Rae, Michael","Lowry, Michael","McGrath, Finian","McGrath, Mattie","Pringle, Thomas","Ross, Shane","Wallace, Mick","Broughan, Thomas P.","Burton, Joan","Gilmore, Eamon","Hannigan, Dominic","Keaveney, Colm","Kelly, Alan","Lynch, Kathleen","Lyons, John","McCarthy, Michael","McNamara, Michael","Nash, Gerald","Nulty, Patrick","Penrose, Willie","Phelan, Ann","Quinn, Ruairí","Sherlock, Sean","Shortall, Róisín","Spring, Arthur","Tuffy, Joanna","Boyd Barrett, Richard","Adams, Gerry","Ellis, Dessie","McDonald, Mary Lou","McLellan, Sandra","Tóibín, Peadar","Barrett, Seán"] }