{ "title" : "Reform of Judicial Appointment Procedures Bill 2013 - Second Stage (Postponed Division). That the Bill now read a second time.","date" : { "date" : "2014-06-10","time" : "17:27:00","weekday" : "Tuesday"},"yes" : ["Calleary, Dara","Cowen, Barry","Kelleher, Billy","Kirk, Seamus","Kitt, Michael P.","Martin, Micheál","McConalogue, Charlie","McGrath, Michael","McGuinness, John","O'Dea, Willie","Ó Cuív, Éamon","Ó Fearghaíl, Seán","Smith, Brendan","Troy, Robert","Daly, Clare","Donnelly, Stephen S.","Grealish, Noel","Healy-Rae, Michael","Healy, Seamus","Lowry, Michael","McGrath, Finian","McGrath, Mattie","Murphy, Catherine","O'Sullivan, Maureen","Pringle, Thomas","Ross, Shane","Wallace, Mick","Broughan, Thomas P.","Shortall, Róisín","Boyd Barrett, Richard","Collins, Joan","Adams, Gerry","Colreavy, Michael","Crowe, Seán","Doherty, Pearse","Ellis, Dessie","Ferris, Martin","Mac Lochlainn, Pádraig","McDonald, Mary Lou","McLellan, Sandra","O'Brien, Jonathan","Ó Caoláin, Caoimhghín","Ó Snodaigh, Aengus","Stanley, Brian"],"no" : ["Barry, Tom","Breen, Pat","Butler, Ray","Buttimer, Jerry","Byrne, Catherine","Cannon, Ciarán","Carey, Joe","Coffey, Paudie","Collins, Áine","Conlan, Seán","Connaughton, Paul J.","Coonan, Noel","Corcoran Kennedy, Marcella","Coveney, Simon","Deenihan, Jimmy","Deering, Pat","Doherty, Regina","Doyle, Andrew","Durkan, Bernard J.","English, Damien","Feighan, Frank","Fitzgerald, Frances","Flanagan, Terence","Griffin, Brendan","Harrington, Noel","Harris, Simon","Hayes, Tom","Heydon, Martin","Hogan, Phil","Humphreys, Heather","Keating, Derek","Kehoe, Paul","Kenny, Enda","Kyne, Seán","Lawlor, Anthony","McEntee, Helen","McFadden, Gabrielle","McGinley, Dinny","McLoughlin, Tony","Mulherin, Michelle","Murphy, Dara","Murphy, Eoghan","Neville, Dan","O'Donnell, Kieran","O'Donovan, Patrick","O'Dowd, Fergus","O'Mahony, John","O'Reilly, Joe","Perry, John","Phelan, John Paul","Reilly, James","Ring, Michael","Shatter, Alan","Stanton, David","Walsh, Brian","Burton, Joan","Byrne, Eric","Conaghan, Michael","Conway, Ciara","Dowds, Robert","Ferris, Anne","Gilmore, Eamon","Hannigan, Dominic","Howlin, Brendan","Humphreys, Kevin","Kelly, Alan","Kenny, Seán","Lynch, Ciarán","Lynch, Kathleen","Lyons, John","Maloney, Eamonn","McCarthy, Michael","McNamara, Michael","Nash, Gerald","Nolan, Derek","O'Sullivan, Jan","Phelan, Ann","Quinn, Ruairí","Rabbitte, Pat","Ryan, Brendan","Sherlock, Sean","Stagg, Emmet","Wall, Jack","White, Alex"], "absent" : ["Browne, John","Collins, Niall","Dooley, Timmy","Fleming, Sean","Moynihan, Michael","Bannon, James","Bruton, Richard","Creed, Michael","Creighton, Lucinda","Daly, Jim","Deasy, John","Donohoe, Paschal","Farrell, Alan","Fitzpatrick, Peter","Flanagan, Charles","Hayes, Brian","Mathews, Peter","McFadden, Nicky","McHugh, Joe","Mitchell O'Connor, Mary","Mitchell, Olivia","Naughten, Denis","Noonan, Michael","Timmins, Billy","Twomey, Liam","Varadkar, Leo","Flanagan, Luke 'Ming'","Fleming, Tom","Halligan, John","Costello, Joe","Keaveney, Colm","Nulty, Patrick","Ó Ríordáin, Aodhán","Penrose, Willie","Spring, Arthur","Tuffy, Joanna","Tóibín, Peadar","Coppinger, Ruth M.","Higgins, Joe","Barrett, Seán"] }